ssegmetrics/__init__.py
ssegmetrics/metrics.py
ssegmetrics/sample.py
ssegmetrics-0.1.0.dist-info/LICENSE
ssegmetrics-0.1.0.dist-info/METADATA
ssegmetrics-0.1.0.dist-info/WHEEL
ssegmetrics-0.1.0.dist-info/top_level.txt
ssegmetrics-0.1.0.dist-info/RECORD
