Metadata-Version: 2.1
Name: ssegmetrics
Version: 0.1.0
Summary: Metrics about segmentation based on Ptyhon.
Home-page: https://github.com/geoyee/segMetrics
Author: geoyee
Author-email: geoyee@yeah.net
License: UNKNOWN
Platform: UNKNOWN
Classifier: Programming Language :: Python :: 3
Classifier: Programming Language :: Python :: 3.8
Classifier: License :: OSI Approved :: Apache Software License
Requires-Dist: matplotlib
Requires-Dist: numpy
Requires-Dist: opencv-python
